ccpn_project_checker/DiskModelChecker.py
ccpn_project_checker/MetaModelWalker.py
ccpn_project_checker/__init__.py
ccpn_project_checker/main.py
ccpn_project_checker/test.py
ccpn_project_checker/util.py
ccpn_project_checker/model_info/data_file_names.txt
ccpn_project_checker/model_info/v_3_1_0_guid_to_storage_location.json
ccpn_project_checker/model_info/v_3_1_0_object_info.json
ccpn_project_checker/model_info/v_3_1_0_short_name_to_guid.json
ccpn_project_checker/optional/__init__.py
ccpn_project_checker/optional/abstract_optional.py
ccpn_project_checker/optional/compatible_abc.py
ccpn_project_checker/optional/exceptions.py
ccpn_project_checker/optional/nothing.py
ccpn_project_checker/optional/optional.py
ccpn_project_checker/optional/something.py
ccpn_project_checker/test_data/cli_test_output.txt
ccpn_project_checker/test_data/project_is_file.ccpn
ccpn_project_checker/test_data/bad_memops_root_xml.ccpn/ccpnv3/memops/Implementation/bad_memops_root_xml.xml
ccpn_project_checker/test_data/basic_exo_links_not_found.ccpn/ccpnv3/memops/Implementation/basic_exo_links_not_found.xml
ccpn_project_checker/test_data/delayed_errors/bad_embedded_exo_link_0_child_elements.ccpn/ccpnv3/ccp/lims/RefSampleComponent/default+default_user_2024-02-24-15-54-35-583_00003.xml
ccpn_project_checker/test_data/delayed_errors/bad_embedded_exo_link_0_child_elements.ccpn/ccpnv3/ccp/lims/Sample/default+default_user_2024-02-24-15-54-35-583_00002.xml
ccpn_project_checker/test_data/delayed_errors/bad_embedded_exo_link_0_child_elements.ccpn/ccpnv3/ccp/molecule/MolSystem/default+default_user_2024-02-24-15-54-35-583_00004.xml
ccpn_project_checker/test_data/delayed_errors/bad_embedded_exo_link_0_child_elements.ccpn/ccpnv3/ccp/nmr/Nmr/default+default_user_2024-02-24-15-54-35-583_00001.xml
ccpn_project_checker/test_data/delayed_errors/bad_embedded_exo_link_0_child_elements.ccpn/ccpnv3/ccpnmr/gui/Task/user+View+default_user_2024-02-24-15-54-35-583_00006.xml
ccpn_project_checker-0.1.17.dist-info/METADATA
ccpn_project_checker-0.1.17.dist-info/WHEEL
ccpn_project_checker-0.1.17.dist-info/entry_points.txt
ccpn_project_checker-0.1.17.dist-info/licenses/LICENSE.txt
ccpn_project_checker-0.1.17.dist-info/RECORD
