Metadata-Version: 2.3
Name: ccpn-project-checker
Version: 0.1.17
Summary: A project checker for ccpn v3+ projects
Author-email: varioustoxins <garyt.and.sarahb@gmail.com>
License-File: LICENSE.txt
Requires-Python: >=3.9
Requires-Dist: lxml>=4.9.0
Requires-Dist: pytest>=7.4.0
Requires-Dist: time-machine>=2.14.1
